README.md
setup.py
SaturnTool/__init__.py
SaturnTool.egg-info/PKG-INFO
SaturnTool.egg-info/SOURCES.txt
SaturnTool.egg-info/dependency_links.txt
SaturnTool.egg-info/top_level.txt