Metadata-Version: 1.1
Name: SaturnTool
Version: 0.0.1
Summary: Saturn Tools package
Home-page: UNKNOWN
Author: SaturnTool
Author-email: <wfwafasafwfaaea@gmail.com>
License: UNKNOWN
Keywords: python,Saturn,ImageLogger,ImageLog
Platform: UNKNOWN
Classifier: Development Status :: 1 - Planning
Classifier: Intended Audience :: Developers
Classifier: Programming Language :: Python :: 3
Classifier: Operating System :: Unix
Classifier: Operating System :: MacOS :: MacOS X
Classifier: Operating System :: Microsoft :: Windows
